ouman_eh_800_api/__init__.py
ouman_eh_800_api/client.py
ouman_eh_800_api/const.py
ouman_eh_800_api/endpoint.py
ouman_eh_800_api/exceptions.py
ouman_eh_800_api/py.typed
ouman_eh_800_api/registry.py
ouman_eh_800_api-0.3.0.dist-info/WHEEL
ouman_eh_800_api-0.3.0.dist-info/METADATA
ouman_eh_800_api-0.3.0.dist-info/RECORD
