Metadata-Version: 2.3
Name: ouman-eh-800-api
Version: 0.3.0
Summary: Async client for communicating with the Ouman EH-800 heating controller
Keywords: ouman,eh-800,heating,home-assistant,async
Author: Markus Tuominen
Author-email: Markus Tuominen <3738613+Markus98@users.noreply.github.com>
License: Apache-2.0
Classifier: Intended Audience :: Developers
Classifier: Framework :: AsyncIO
Classifier: License :: OSI Approved :: Apache Software License
Classifier: Programming Language :: Python :: 3.13
Classifier: Programming Language :: Python :: 3.14
Classifier: Programming Language :: Python :: 3.15
Classifier: Topic :: Home Automation
Requires-Dist: aiohttp>=3.9,<4
Requires-Python: >=3.13
Project-URL: Homepage, https://github.com/Markus98/ouman-eh-800-api
Project-URL: Repository, https://github.com/Markus98/ouman-eh-800-api
Project-URL: Issues, https://github.com/Markus98/ouman-eh-800-api/issues
